.gitignore
AUTHORS
COPYING.txt
MANIFEST.in
NEWS.txt
README.txt
TODO.txt
development.ini
getdeps.py
setup.cfg
setup.py
test.ini
docs/index.txt
docs/internals.txt
docs/dev/README.txt
docs/dev/design.txt
docs/dev/gazmail.txt
docs/dev/markup.txt
docs/html/NEWS.html
docs/html/README.html
docs/html/index.html
docs/html/internals.html
gazest/__init__.py
gazest/websetup.py
gazest.egg-info/PKG-INFO
gazest.egg-info/SOURCES.txt
gazest.egg-info/dependency_links.txt
gazest.egg-info/entry_points.txt
gazest.egg-info/paste_deploy_config.ini_tmpl
gazest.egg-info/paster_plugins.txt
gazest.egg-info/requires.txt
gazest.egg-info/requires.txt~
gazest.egg-info/top_level.txt
gazest/config/__init__.py
gazest/config/environment.py
gazest/config/middleware.py
gazest/config/routing.py
gazest/controllers/__init__.py
gazest/controllers/admin.py
gazest/controllers/dagimage.py
gazest/controllers/error.py
gazest/controllers/gazmail.py
gazest/controllers/home.py
gazest/controllers/robots.py
gazest/controllers/search.py
gazest/controllers/template.py
gazest/controllers/visitor.py
gazest/controllers/wiki.py
gazest/extra_data/README.txt
gazest/extra_data/__init__.py
gazest/extra_data/default_not_found_page.txt
gazest/extra_data/default_stub_page.txt
gazest/i18n/__init__.py
gazest/lib/__init__.py
gazest/lib/ancestor.py
gazest/lib/app_globals.py
gazest/lib/auth_util.py
gazest/lib/base.py
gazest/lib/dag.py
gazest/lib/formutil.py
gazest/lib/helpers.py
gazest/lib/install_util.py
gazest/lib/iplib.py
gazest/lib/markdown.py
gazest/lib/markup.py
gazest/lib/openidutil.py
gazest/lib/paste_deploy_config.ini_tmpl
gazest/lib/request_util.py
gazest/lib/wiki_macros.py
gazest/lib/wiki_util.py
gazest/lib/wikipage.py
gazest/model/__init__.py
gazest/public/favicon.ico
gazest/public/css/simple.css
gazest/public/css/simple.css~
gazest/public/css/site.css
gazest/public/img/cr22-action-button_cancel.png
gazest/public/img/cr22-action-button_ok.png
gazest/public/img/cr32-action-button_cancel.png
gazest/public/img/cr32-action-button_ok.png
gazest/public/img/feed.png
gazest/public/img/top-banner.jpg
gazest/scripts/__init__.py
gazest/scripts/god_mode.py
gazest/templates/about.mako
gazest/templates/admin_boycott_form.mako
gazest/templates/autohandler
gazest/templates/base.mako
gazest/templates/common_defs.mako
