Metadata-Version: 1.0
Name: gazest
Version: 0.3.9
Summary: A wiki based community engine
Home-page: http://ygingras.net/gazest
Author: Yannick Gingras
Author-email: ygingras@ygingras.net
License: GPL v3 or later
Platform: UNKNOWN
